Workbook

Sheet Решение
A1: Решение: бюджет маркетинга на следующий год
A2: Доля канала меняется пропорционально его ROAS к среднему, в пределах потолка и пола. Параметры — на листе «Данные».
A3: Общий бюджет следующего года | B3: =ROUND(Данные!B12*(1+Данные!$B$17),-3)
A5: Канал продаж | B5: Бюджет этого года, ₽ | C5: ROAS | D5: ROMI | E5: Множитель по ROAS | F5: Множитель с ограничениями | G5: Вес | H5: Доля в новом бюджете | I5: НОВЫЙ БЮДЖЕТ, ₽ | J5: Изменение, ₽ | K5: Изменение, % | L5: Решение | M5: Ожидаемая выручка (верхняя оценка), ₽
A6: =Анализ!A5 | B6: =Анализ!B5 | C6: =Анализ!M5 | D6: =Анализ!P5 | E6: =IF(Анализ!$M$12=0,1,(C6/Анализ!$M$12)^Данные!$B$18) | F6: =MIN(MAX(E6,Данные!$B$20),Данные!$B$19) | G6: =B6*F6 | H6: =IF($G$13=0,0,G6/$G$13) | I6: =ROUND(H6*$B$3,0) | J6: =I6-B6 | K6: =IF(B6=0,0,I6/B6-1) | L6: =IF(K6>Данные!$B$21,"Увеличить",IF(K6<-Данные!$B$21,"Сократить","Сохранить")) | M6: =I6*C6
A7: =Анализ!A6 | B7: =Анализ!B6 | C7: =Анализ!M6 | D7: =Анализ!P6 | E7: =IF(Анализ!$M$12=0,1,(C7/Анализ!$M$12)^Данные!$B$18) | F7: =MIN(MAX(E7,Данные!$B$20),Данные!$B$19) | G7: =B7*F7 | H7: =IF($G$13=0,0,G7/$G$13) | I7: =ROUND(H7*$B$3,0) | J7: =I7-B7 | K7: =IF(B7=0,0,I7/B7-1) | L7: =IF(K7>Данные!$B$21,"Увеличить",IF(K7<-Данные!$B$21,"Сократить","Сохранить")) | M7: =I7*C7
A8: =Анализ!A7 | B8: =Анализ!B7 | C8: =Анализ!M7 | D8: =Анализ!P7 | E8: =IF(Анализ!$M$12=0,1,(C8/Анализ!$M$12)^Данные!$B$18) | F8: =MIN(MAX(E8,Данные!$B$20),Данные!$B$19) | G8: =B8*F8 | H8: =IF($G$13=0,0,G8/$G$13) | I8: =ROUND(H8*$B$3,0) | J8: =I8-B8 | K8: =IF(B8=0,0,I8/B8-1) | L8: =IF(K8>Данные!$B$21,"Увеличить",IF(K8<-Данные!$B$21,"Сократить","Сохранить")) | M8: =I8*C8
A9: =Анализ!A8 | B9: =Анализ!B8 | C9: =Анализ!M8 | D9: =Анализ!P8 | E9: =IF(Анализ!$M$12=0,1,(C9/Анализ!$M$12)^Данные!$B$18) | F9: =MIN(MAX(E9,Данные!$B$20),Данные!$B$19) | G9: =B9*F9 | H9: =IF($G$13=0,0,G9/$G$13) | I9: =ROUND(H9*$B$3,0) | J9: =I9-B9 | K9: =IF(B9=0,0,I9/B9-1) | L9: =IF(K9>Данные!$B$21,"Увеличить",IF(K9<-Данные!$B$21,"Сократить","Сохранить")) | M9: =I9*C9
A10: =Анализ!A9 | B10: =Анализ!B9 | C10: =Анализ!M9 | D10: =Анализ!P9 | E10: =IF(Анализ!$M$12=0,1,(C10/Анализ!$M$12)^Данные!$B$18) | F10: =MIN(MAX(E10,Данные!$B$20),Данные!$B$19) | G10: =B10*F10 | H10: =IF($G$13=0,0,G10/$G$13) | I10: =ROUND(H10*$B$3,0) | J10: =I10-B10 | K10: =IF(B10=0,0,I10/B10-1) | L10: =IF(K10>Данные!$B$21,"Увеличить",IF(K10<-Данные!$B$21,"Сократить","Сохранить")) | M10: =I10*C10
A11: =Анализ!A10 | B11: =Анализ!B10 | C11: =Анализ!M10 | D11: =Анализ!P10 | E11: =IF(Анализ!$M$12=0,1,(C11/Анализ!$M$12)^Данные!$B$18) | F11: =MIN(MAX(E11,Данные!$B$20),Данные!$B$19) | G11: =B11*F11 | H11: =IF($G$13=0,0,G11/$G$13) | I11: =ROUND(H11*$B$3,0) | J11: =I11-B11 | K11: =IF(B11=0,0,I11/B11-1) | L11: =IF(K11>Данные!$B$21,"Увеличить",IF(K11<-Данные!$B$21,"Сократить","Сохранить")) | M11: =I11*C11
A12: =Анализ!A11 | B12: =Анализ!B11 | C12: =Анализ!M11 | D12: =Анализ!P11 | E12: =IF(Анализ!$M$12=0,1,(C12/Анализ!$M$12)^Данные!$B$18) | F12: =MIN(MAX(E12,Данные!$B$20),Данные!$B$19) | G12: =B12*F12 | H12: =IF($G$13=0,0,G12/$G$13) | I12: =ROUND(H12*$B$3,0) | J12: =I12-B12 | K12: =IF(B12=0,0,I12/B12-1) | L12: =IF(K12>Данные!$B$21,"Увеличить",IF(K12<-Данные!$B$21,"Сократить","Сохранить")) | M12: =I12*C12
A13: ИТОГО | B13: =SUM(B6:B12) | C13: =Анализ!M12 | D13: =Анализ!P12 | G13: =SUM(G6:G12) | H13: =SUM(H6:H12) | I13: =SUM(I6:I12) | J13: =SUM(J6:J12) | K13: =IF(B13=0,0,I13/B13-1) | M13: =SUM(M6:M12)
A15: ВЫВОДЫ ДЛЯ ПИТЧА
A16: Больше всего денег получает | B16: =INDEX(A6:A12,MATCH(MAX(I6:I12),I6:I12,0))&" — "&FIXED(MAX(I6:I12),0)&" ₽"
A17: Самый эффективный канал (ROAS) | B17: =INDEX(A6:A12,MATCH(MAX(C6:C12),C6:C12,0))&" — ROAS "&FIXED(MAX(C6:C12),1)
A18: Самый слабый канал (ROAS) | B18: =INDEX(A6:A12,MATCH(MIN(C6:C12),C6:C12,0))&" — ROAS "&FIXED(MIN(C6:C12),1)
A19: Каналов работает в убыток (ROMI < 0) | B19: =COUNTIF(D6:D12,"<0")
A20: Каналов увеличиваем / сокращаем | B20: =COUNTIF(L6:L12,"Увеличить")&" / "&COUNTIF(L6:L12,"Сократить")
A21: Ожидаемый ROAS с новым бюджетом | B21: =IF(I13=0,0,M13/I13)
A22: ROAS этого года для сравнения | B22: =C13
A24: Ожидаемая выручка — верхняя оценка: при масштабировании ROAS канала обычно снижается, поэтому новые деньги стоит выдавать поэтапно и проверять ROAS ежеквартально.

Sheet Данные
A1: Кейс 2. Каналы продаж — исходные данные за год
A2: ПРИМЕР ДАННЫХ. Замените жёлтые ячейки реальными цифрами кейса — анализ, воронка и решение пересчитаются сами.
A4: Канал продаж | B4: Расходы за год, ₽ | C4: Показы / охват | D4: Переходы (клики, визиты) | E4: Интерес (корзина / заявка) | F4: Заказы | G4: Выручка, ₽
A5: Таргет ВКонтакте | B5: 900000 | C5: 4500000 | D5: 36000 | E5: 3600 | F5: 720 | G5: 1728000
A6: Блогеры и инфлюенсеры | B6: 1200000 | C6: 6000000 | D6: 90000 | E6: 9000 | F6: 1800 | G6: 4680000
A7: Реклама на маркетплейсах | B7: 1500000 | C7: 12000000 | D7: 240000 | E7: 24000 | F7: 4800 | G7: 10080000
A8: Яндекс Директ | B8: 800000 | C8: 2000000 | D8: 40000 | E8: 2800 | F8: 560 | G8: 1400000
A9: SEO и контент сайта | B9: 400000 | C9: 1500000 | D9: 45000 | E9: 4500 | F9: 1125 | G9: 3037500
A10: Email и Telegram-рассылки | B10: 250000 | C10: 400000 | D10: 20000 | E10: 3000 | F10: 1000 | G10: 3000000
A11: Офлайн: pop-up и фестивали | B11: 700000 | C11: 150000 | D11: 15000 | E11: 3000 | F11: 1050 | G11: 2100000
A12: ИТОГО | B12: =SUM(B5:B11) | C12: =SUM(C5:C11) | D12: =SUM(D5:D11) | E12: =SUM(E5:E11) | F12: =SUM(F5:F11) | G12: =SUM(G5:G11)
A15: ПАРАМЕТРЫ РЕШЕНИЯ
A16: Валовая маржа футболки | B16: 0.55 | C16: доля выручки, остающаяся после себестоимости
A17: Рост общего бюджета на следующий год | B17: 0.15 | C17: бюджет следующего года = расходы этого × (1 + рост)
A18: Чувствительность к ROAS | B18: 1 | C18: 1 — доля канала меняется пропорционально его ROAS к среднему
A19: Максимальный рост канала, × | B19: 2 | C19: потолок: канал не масштабируется бесконечно — аудитория выгорает
A20: Минимальное сохранение канала, × | B20: 0.5 | C20: пол: слабый канал режем, но не выключаем — оставляем на тест
A21: Порог решения «увеличить / сократить» | B21: 0.1 | C21: изменение меньше порога считаем «сохранить»
A23: Как читать этапы воронки
A24: Показы / охват — сколько людей увидели рекламу (для рассылок — доставлено, для офлайна — посетители события).
A25: Переходы — клики на сайт или карточку товара (для офлайна — подошли к стенду).
A26: Интерес — добавили в корзину или оставили заявку (для офлайна — примерили).
A27: Заказы — оплаченные покупки. Выручка — деньги от этих заказов.

Sheet Анализ
A1: Эффективность каналов
A2: ROAS = выручка / расходы. ROMI учитывает маржу: сколько валовой прибыли сверх вложенного приносит рубль.
A4: Канал продаж | B4: Расходы, ₽ | C4: Выручка, ₽ | D4: Заказы | E4: Средний чек, ₽ | F4: CTR (показ → переход) | G4: CR (переход → интерес) | H4: CR (интерес → заказ) | I4: Конверсия показ → заказ | J4: Цена перехода (CPC), ₽ | K4: Цена интереса (CPL), ₽ | L4: Цена заказа (CAC), ₽ | M4: ROAS | N4: ДРР (расходы / выручка) | O4: Валовая прибыль, ₽ | P4: ROMI | Q4: Доля бюджета | R4: Доля выручки | S4: Место по ROAS | T4: Оценка канала
A5: =Данные!A5 | B5: =Данные!B5 | C5: =Данные!G5 | D5: =Данные!F5 | E5: =IF(D5=0,0,C5/D5) | F5: =IF(Данные!C5=0,0,Данные!D5/Данные!C5) | G5: =IF(Данные!D5=0,0,Данные!E5/Данные!D5) | H5: =IF(Данные!E5=0,0,Данные!F5/Данные!E5) | I5: =IF(Данные!C5=0,0,Данные!F5/Данные!C5) | J5: =IF(Данные!D5=0,0,B5/Данные!D5) | K5: =IF(Данные!E5=0,0,B5/Данные!E5) | L5: =IF(D5=0,0,B5/D5) | M5: =IF(B5=0,0,C5/B5) | N5: =IF(C5=0,0,B5/C5) | O5: =C5*Данные!$B$16 | P5: =IF(B5=0,0,(O5-B5)/B5) | Q5: =IF($B$12=0,0,B5/$B$12) | R5: =IF($C$12=0,0,C5/$C$12) | S5: =RANK(M5,$M$5:$M$11) | T5: =IF(M5<$B$15,"Убыточен — сократить",IF(M5>=$M$12,"Лидер — наращивать","Ниже среднего — оптимизировать"))
A6: =Данные!A6 | B6: =Данные!B6 | C6: =Данные!G6 | D6: =Данные!F6 | E6: =IF(D6=0,0,C6/D6) | F6: =IF(Данные!C6=0,0,Данные!D6/Данные!C6) | G6: =IF(Данные!D6=0,0,Данные!E6/Данные!D6) | H6: =IF(Данные!E6=0,0,Данные!F6/Данные!E6) | I6: =IF(Данные!C6=0,0,Данные!F6/Данные!C6) | J6: =IF(Данные!D6=0,0,B6/Данные!D6) | K6: =IF(Данные!E6=0,0,B6/Данные!E6) | L6: =IF(D6=0,0,B6/D6) | M6: =IF(B6=0,0,C6/B6) | N6: =IF(C6=0,0,B6/C6) | O6: =C6*Данные!$B$16 | P6: =IF(B6=0,0,(O6-B6)/B6) | Q6: =IF($B$12=0,0,B6/$B$12) | R6: =IF($C$12=0,0,C6/$C$12) | S6: =RANK(M6,$M$5:$M$11) | T6: =IF(M6<$B$15,"Убыточен — сократить",IF(M6>=$M$12,"Лидер — наращивать","Ниже среднего — оптимизировать"))
A7: =Данные!A7 | B7: =Данные!B7 | C7: =Данные!G7 | D7: =Данные!F7 | E7: =IF(D7=0,0,C7/D7) | F7: =IF(Данные!C7=0,0,Данные!D7/Данные!C7) | G7: =IF(Данные!D7=0,0,Данные!E7/Данные!D7) | H7: =IF(Данные!E7=0,0,Данные!F7/Данные!E7) | I7: =IF(Данные!C7=0,0,Данные!F7/Данные!C7) | J7: =IF(Данные!D7=0,0,B7/Данные!D7) | K7: =IF(Данные!E7=0,0,B7/Данные!E7) | L7: =IF(D7=0,0,B7/D7) | M7: =IF(B7=0,0,C7/B7) | N7: =IF(C7=0,0,B7/C7) | O7: =C7*Данные!$B$16 | P7: =IF(B7=0,0,(O7-B7)/B7) | Q7: =IF($B$12=0,0,B7/$B$12) | R7: =IF($C$12=0,0,C7/$C$12) | S7: =RANK(M7,$M$5:$M$11) | T7: =IF(M7<$B$15,"Убыточен — сократить",IF(M7>=$M$12,"Лидер — наращивать","Ниже среднего — оптимизировать"))
A8: =Данные!A8 | B8: =Данные!B8 | C8: =Данные!G8 | D8: =Данные!F8 | E8: =IF(D8=0,0,C8/D8) | F8: =IF(Данные!C8=0,0,Данные!D8/Данные!C8) | G8: =IF(Данные!D8=0,0,Данные!E8/Данные!D8) | H8: =IF(Данные!E8=0,0,Данные!F8/Данные!E8) | I8: =IF(Данные!C8=0,0,Данные!F8/Данные!C8) | J8: =IF(Данные!D8=0,0,B8/Данные!D8) | K8: =IF(Данные!E8=0,0,B8/Данные!E8) | L8: =IF(D8=0,0,B8/D8) | M8: =IF(B8=0,0,C8/B8) | N8: =IF(C8=0,0,B8/C8) | O8: =C8*Данные!$B$16 | P8: =IF(B8=0,0,(O8-B8)/B8) | Q8: =IF($B$12=0,0,B8/$B$12) | R8: =IF($C$12=0,0,C8/$C$12) | S8: =RANK(M8,$M$5:$M$11) | T8: =IF(M8<$B$15,"Убыточен — сократить",IF(M8>=$M$12,"Лидер — наращивать","Ниже среднего — оптимизировать"))
A9: =Данные!A9 | B9: =Данные!B9 | C9: =Данные!G9 | D9: =Данные!F9 | E9: =IF(D9=0,0,C9/D9) | F9: =IF(Данные!C9=0,0,Данные!D9/Данные!C9) | G9: =IF(Данные!D9=0,0,Данные!E9/Данные!D9) | H9: =IF(Данные!E9=0,0,Данные!F9/Данные!E9) | I9: =IF(Данные!C9=0,0,Данные!F9/Данные!C9) | J9: =IF(Данные!D9=0,0,B9/Данные!D9) | K9: =IF(Данные!E9=0,0,B9/Данные!E9) | L9: =IF(D9=0,0,B9/D9) | M9: =IF(B9=0,0,C9/B9) | N9: =IF(C9=0,0,B9/C9) | O9: =C9*Данные!$B$16 | P9: =IF(B9=0,0,(O9-B9)/B9) | Q9: =IF($B$12=0,0,B9/$B$12) | R9: =IF($C$12=0,0,C9/$C$12) | S9: =RANK(M9,$M$5:$M$11) | T9: =IF(M9<$B$15,"Убыточен — сократить",IF(M9>=$M$12,"Лидер — наращивать","Ниже среднего — оптимизировать"))
A10: =Данные!A10 | B10: =Данные!B10 | C10: =Данные!G10 | D10: =Данные!F10 | E10: =IF(D10=0,0,C10/D10) | F10: =IF(Данные!C10=0,0,Данные!D10/Данные!C10) | G10: =IF(Данные!D10=0,0,Данные!E10/Данные!D10) | H10: =IF(Данные!E10=0,0,Данные!F10/Данные!E10) | I10: =IF(Данные!C10=0,0,Данные!F10/Данные!C10) | J10: =IF(Данные!D10=0,0,B10/Данные!D10) | K10: =IF(Данные!E10=0,0,B10/Данные!E10) | L10: =IF(D10=0,0,B10/D10) | M10: =IF(B10=0,0,C10/B10) | N10: =IF(C10=0,0,B10/C10) | O10: =C10*Данные!$B$16 | P10: =IF(B10=0,0,(O10-B10)/B10) | Q10: =IF($B$12=0,0,B10/$B$12) | R10: =IF($C$12=0,0,C10/$C$12) | S10: =RANK(M10,$M$5:$M$11) | T10: =IF(M10<$B$15,"Убыточен — сократить",IF(M10>=$M$12,"Лидер — наращивать","Ниже среднего — оптимизировать"))
A11: =Данные!A11 | B11: =Данные!B11 | C11: =Данные!G11 | D11: =Данные!F11 | E11: =IF(D11=0,0,C11/D11) | F11: =IF(Данные!C11=0,0,Данные!D11/Данные!C11) | G11: =IF(Данные!D11=0,0,Данные!E11/Данные!D11) | H11: =IF(Данные!E11=0,0,Данные!F11/Данные!E11) | I11: =IF(Данные!C11=0,0,Данные!F11/Данные!C11) | J11: =IF(Данные!D11=0,0,B11/Данные!D11) | K11: =IF(Данные!E11=0,0,B11/Данные!E11) | L11: =IF(D11=0,0,B11/D11) | M11: =IF(B11=0,0,C11/B11) | N11: =IF(C11=0,0,B11/C11) | O11: =C11*Данные!$B$16 | P11: =IF(B11=0,0,(O11-B11)/B11) | Q11: =IF($B$12=0,0,B11/$B$12) | R11: =IF($C$12=0,0,C11/$C$12) | S11: =RANK(M11,$M$5:$M$11) | T11: =IF(M11<$B$15,"Убыточен — сократить",IF(M11>=$M$12,"Лидер — наращивать","Ниже среднего — оптимизировать"))
A12: ИТОГО / среднее по компании | B12: =Данные!B12 | C12: =Данные!G12 | D12: =Данные!F12 | E12: =IF(D12=0,0,C12/D12) | F12: =IF(Данные!C12=0,0,Данные!D12/Данные!C12) | G12: =IF(Данные!D12=0,0,Данные!E12/Данные!D12) | H12: =IF(Данные!E12=0,0,Данные!F12/Данные!E12) | I12: =IF(Данные!C12=0,0,Данные!F12/Данные!C12) | J12: =IF(Данные!D12=0,0,B12/Данные!D12) | K12: =IF(Данные!E12=0,0,B12/Данные!E12) | L12: =IF(D12=0,0,B12/D12) | M12: =IF(B12=0,0,C12/B12) | N12: =IF(C12=0,0,B12/C12) | O12: =C12*Данные!$B$16 | P12: =IF(B12=0,0,(O12-B12)/B12) | Q12: =IF($B$12=0,0,B12/$B$12) | R12: =IF($C$12=0,0,C12/$C$12)
A14: ОРИЕНТИРЫ
A15: ROAS безубыточности (1 / маржа) | B15: =1/Данные!$B$16 | C15: ниже — канал не окупает рекламу даже валовой прибылью
A16: Средний ROAS компании | B16: =M12 | C16: выше — канал работает лучше среднего, в него выгоднее доливать

Sheet Воронка
A1: Воронка продаж
A2: Общая воронка компании и воронка по каждому каналу. Конверсия шага = этап / предыдущий этап.
A4: Этап воронки | B4: Люди | C4: Конверсия шага | D4: Конверсия от охвата | G4: Этап | H4: отступ | I4: Люди
A5: Показы / охват | B5: =Данные!C12 | C5: — | D5: =IF($B$5=0,0,B5/$B$5) | G5: Переходы | H5: =($B$6-B6)/2 | I5: =B6
A6: Переходы | B6: =Данные!D12 | C6: =IF(B5=0,0,B6/B5) | D6: =IF($B$5=0,0,B6/$B$5) | G6: Интерес (корзина / заявка) | H6: =($B$6-B7)/2 | I6: =B7
A7: Интерес (корзина / заявка) | B7: =Данные!E12 | C7: =IF(B6=0,0,B7/B6) | D7: =IF($B$5=0,0,B7/$B$5) | G7: Заказы | H7: =($B$6-B8)/2 | I7: =B8
A8: Заказы | B8: =Данные!F12 | C8: =IF(B7=0,0,B8/B7) | D8: =IF($B$5=0,0,B8/$B$5)
A12: ВОРОНКА ПО КАНАЛАМ
A13: Канал продаж | B13: Показы / охват | C13: Переходы | D13: Интерес | E13: Заказы | F13: Показ → переход | G13: Переход → интерес | H13: Интерес → заказ | I13: Показ → заказ | J13: Узкое место
A14: =Данные!A5 | B14: =Данные!C5 | C14: =Данные!D5 | D14: =Данные!E5 | E14: =Данные!F5 | F14: =IF(B14=0,0,C14/B14) | G14: =IF(C14=0,0,D14/C14) | H14: =IF(D14=0,0,E14/D14) | I14: =IF(B14=0,0,E14/B14) | J14: =IF(F14/F$21<=MIN(G14/G$21,H14/H$21),"клик: показ → переход",IF(G14/G$21<=H14/H$21,"корзина: переход → интерес","оплата: интерес → заказ"))
A15: =Данные!A6 | B15: =Данные!C6 | C15: =Данные!D6 | D15: =Данные!E6 | E15: =Данные!F6 | F15: =IF(B15=0,0,C15/B15) | G15: =IF(C15=0,0,D15/C15) | H15: =IF(D15=0,0,E15/D15) | I15: =IF(B15=0,0,E15/B15) | J15: =IF(F15/F$21<=MIN(G15/G$21,H15/H$21),"клик: показ → переход",IF(G15/G$21<=H15/H$21,"корзина: переход → интерес","оплата: интерес → заказ"))
A16: =Данные!A7 | B16: =Данные!C7 | C16: =Данные!D7 | D16: =Данные!E7 | E16: =Данные!F7 | F16: =IF(B16=0,0,C16/B16) | G16: =IF(C16=0,0,D16/C16) | H16: =IF(D16=0,0,E16/D16) | I16: =IF(B16=0,0,E16/B16) | J16: =IF(F16/F$21<=MIN(G16/G$21,H16/H$21),"клик: показ → переход",IF(G16/G$21<=H16/H$21,"корзина: переход → интерес","оплата: интерес → заказ"))
A17: =Данные!A8 | B17: =Данные!C8 | C17: =Данные!D8 | D17: =Данные!E8 | E17: =Данные!F8 | F17: =IF(B17=0,0,C17/B17) | G17: =IF(C17=0,0,D17/C17) | H17: =IF(D17=0,0,E17/D17) | I17: =IF(B17=0,0,E17/B17) | J17: =IF(F17/F$21<=MIN(G17/G$21,H17/H$21),"клик: показ → переход",IF(G17/G$21<=H17/H$21,"корзина: переход → интерес","оплата: интерес → заказ"))
A18: =Данные!A9 | B18: =Данные!C9 | C18: =Данные!D9 | D18: =Данные!E9 | E18: =Данные!F9 | F18: =IF(B18=0,0,C18/B18) | G18: =IF(C18=0,0,D18/C18) | H18: =IF(D18=0,0,E18/D18) | I18: =IF(B18=0,0,E18/B18) | J18: =IF(F18/F$21<=MIN(G18/G$21,H18/H$21),"клик: показ → переход",IF(G18/G$21<=H18/H$21,"корзина: переход → интерес","оплата: интерес → заказ"))
A19: =Данные!A10 | B19: =Данные!C10 | C19: =Данные!D10 | D19: =Данные!E10 | E19: =Данные!F10 | F19: =IF(B19=0,0,C19/B19) | G19: =IF(C19=0,0,D19/C19) | H19: =IF(D19=0,0,E19/D19) | I19: =IF(B19=0,0,E19/B19) | J19: =IF(F19/F$21<=MIN(G19/G$21,H19/H$21),"клик: показ → переход",IF(G19/G$21<=H19/H$21,"корзина: переход → интерес","оплата: интерес → заказ"))
A20: =Данные!A11 | B20: =Данные!C11 | C20: =Данные!D11 | D20: =Данные!E11 | E20: =Данные!F11 | F20: =IF(B20=0,0,C20/B20) | G20: =IF(C20=0,0,D20/C20) | H20: =IF(D20=0,0,E20/D20) | I20: =IF(B20=0,0,E20/B20) | J20: =IF(F20/F$21<=MIN(G20/G$21,H20/H$21),"клик: показ → переход",IF(G20/G$21<=H20/H$21,"корзина: переход → интерес","оплата: интерес → заказ"))
A21: ИТОГО | B21: =Данные!C12 | C21: =Данные!D12 | D21: =Данные!E12 | E21: =Данные!F12 | F21: =IF(B21=0,0,C21/B21) | G21: =IF(C21=0,0,D21/C21) | H21: =IF(D21=0,0,E21/D21) | I21: =IF(B21=0,0,E21/B21)
