Workbook

Sheet ДДС
A1: месяц | B1: 2025 | C1: 2 | D1: 3 | E1: 4 | F1: 5 | G1: 6 | H1: 7 | I1: 8 | J1: 9 | K1: 10 | L1: 11 | M1: 12 | N1: 13 | O1: 14 | P1: 15 | Q1: 16 | R1: 17 | S1: 18 | T1: 19 | U1: 20 | V1: 21 | W1: 22 | X1: 23 | Y1: 24
A2: ПРИХОД | Z2: =SUM(Z3:Z10)
A3: Продажа товара 1 — футболка «Базовая» | B3: =B4*B5 | C3: =C4*C5 | D3: =D4*D5 | E3: =E4*E5 | F3: =F4*F5 | G3: =G4*G5 | H3: =H4*H5 | I3: =I4*I5 | ... Y3: =Y4*Y5 | Z3: =SUM(B3:Y3)
A4: Количество продаж | B4: =Параметры!$B$12 | C4: =ROUND(B4*(1+IF(C$48<=12,Параметры!$B$13,Параметры!$B$14)),0) | D4: =ROUND(C4*(1+IF(D$48<=12,Параметры!$B$13,Параметры!$B$14)),0) | E4: =ROUND(D4*(1+IF(E$48<=12,Параметры!$B$13,Параметры!$B$14)),0) | F4: =ROUND(E4*(1+IF(F$48<=12,Параметры!$B$13,Параметры!$B$14)),0) | G4: =ROUND(F4*(1+IF(G$48<=12,Параметры!$B$13,Параметры!$B$14)),0) | H4: =ROUND(G4*(1+IF(H$48<=12,Параметры!$B$13,Параметры!$B$14)),0) | I4: =ROUND(H4*(1+IF(I$48<=12,Параметры!$B$13,Параметры!$B$14)),0) | J4: =ROUND(I4*(1+IF(J$48<=12,Параметры!$B$13,Параметры!$B$14)),0) | ... Y4: =ROUND(X4*(1+IF(Y$48<=12,Параметры!$B$13,Параметры!$B$14)),0)
A5: Cредний чек | B5: =Параметры!$B$4 | C5: =Параметры!$B$4 | D5: =Параметры!$B$4 | E5: =Параметры!$B$4 | F5: =Параметры!$B$4 | G5: =Параметры!$B$4 | H5: =Параметры!$B$4 | I5: =Параметры!$B$4 | ... Y5: =Параметры!$B$4
A6: Продажа товара 2 — футболка «Pro» / кастом-принт | B6: =B7*B8 | C6: =C7*C8 | D6: =D7*D8 | E6: =E7*E8 | F6: =F7*F8 | G6: =G7*G8 | H6: =H7*H8 | I6: =I7*I8 | ... Y6: =Y7*Y8 | Z6: =SUM(B6:Y6)
A7: Количество продаж | B7: =IF(B$48<Параметры!$B$15,0,Параметры!$B$16) | C7: =IF(C$48<Параметры!$B$15,0,IF(B7=0,Параметры!$B$16,ROUND(B7*(1+IF(C$48<=12,Параметры!$B$17,Параметры!$B$18)),0))) | D7: =IF(D$48<Параметры!$B$15,0,IF(C7=0,Параметры!$B$16,ROUND(C7*(1+IF(D$48<=12,Параметры!$B$17,Параметры!$B$18)),0))) | E7: =IF(E$48<Параметры!$B$15,0,IF(D7=0,Параметры!$B$16,ROUND(D7*(1+IF(E$48<=12,Параметры!$B$17,Параметры!$B$18)),0))) | F7: =IF(F$48<Параметры!$B$15,0,IF(E7=0,Параметры!$B$16,ROUND(E7*(1+IF(F$48<=12,Параметры!$B$17,Параметры!$B$18)),0))) | G7: =IF(G$48<Параметры!$B$15,0,IF(F7=0,Параметры!$B$16,ROUND(F7*(1+IF(G$48<=12,Параметры!$B$17,Параметры!$B$18)),0))) | H7: =IF(H$48<Параметры!$B$15,0,IF(G7=0,Параметры!$B$16,ROUND(G7*(1+IF(H$48<=12,Параметры!$B$17,Параметры!$B$18)),0))) | I7: =IF(I$48<Параметры!$B$15,0,IF(H7=0,Параметры!$B$16,ROUND(H7*(1+IF(I$48<=12,Параметры!$B$17,Параметры!$B$18)),0))) | J7: =IF(J$48<Параметры!$B$15,0,IF(I7=0,Параметры!$B$16,ROUND(I7*(1+IF(J$48<=12,Параметры!$B$17,Параметры!$B$18)),0))) | ... Y7: =IF(Y$48<Параметры!$B$15,0,IF(X7=0,Параметры!$B$16,ROUND(X7*(1+IF(Y$48<=12,Параметры!$B$17,Параметры!$B$18)),0)))
A8: Средний чек | B8: =Параметры!$B$6 | C8: =Параметры!$B$6 | D8: =Параметры!$B$6 | E8: =Параметры!$B$6 | F8: =Параметры!$B$6 | G8: =Параметры!$B$6 | H8: =Параметры!$B$6 | I8: =Параметры!$B$6 | ... Y8: =Параметры!$B$6
A9: Продажа товара 3 — B2B (командная экипировка, опт) | B9: =IF(B$48<Параметры!$B$19,0,ROUND(Параметры!$B$20*Параметры!$B$8,0)) | C9: =IF(C$48<Параметры!$B$19,0,IF(B9=0,ROUND(Параметры!$B$20*Параметры!$B$8,0),ROUND(B9*(1+Параметры!$B$21),0))) | D9: =IF(D$48<Параметры!$B$19,0,IF(C9=0,ROUND(Параметры!$B$20*Параметры!$B$8,0),ROUND(C9*(1+Параметры!$B$21),0))) | E9: =IF(E$48<Параметры!$B$19,0,IF(D9=0,ROUND(Параметры!$B$20*Параметры!$B$8,0),ROUND(D9*(1+Параметры!$B$21),0))) | F9: =IF(F$48<Параметры!$B$19,0,IF(E9=0,ROUND(Параметры!$B$20*Параметры!$B$8,0),ROUND(E9*(1+Параметры!$B$21),0))) | G9: =IF(G$48<Параметры!$B$19,0,IF(F9=0,ROUND(Параметры!$B$20*Параметры!$B$8,0),ROUND(F9*(1+Параметры!$B$21),0))) | H9: =IF(H$48<Параметры!$B$19,0,IF(G9=0,ROUND(Параметры!$B$20*Параметры!$B$8,0),ROUND(G9*(1+Параметры!$B$21),0))) | I9: =IF(I$48<Параметры!$B$19,0,IF(H9=0,ROUND(Параметры!$B$20*Параметры!$B$8,0),ROUND(H9*(1+Параметры!$B$21),0))) | J9: =IF(J$48<Параметры!$B$19,0,IF(I9=0,ROUND(Параметры!$B$20*Параметры!$B$8,0),ROUND(I9*(1+Параметры!$B$21),0))) | ... Y9: =IF(Y$48<Параметры!$B$19,0,IF(X9=0,ROUND(Параметры!$B$20*Параметры!$B$8,0),ROUND(X9*(1+Параметры!$B$21),0))) | Z9: =SUM(B9:Y9)
A10: ИНВЕСТИЦИИ | B10: =IF(B$48=1,ROUNDUP($B$62*Параметры!$B$63/100000,0)*100000,IF(B$48=Параметры!$B$64,ROUNDUP($B$62*(1-Параметры!$B$63)/100000,0)*100000,0)) | C10: =IF(C$48=1,ROUNDUP($B$62*Параметры!$B$63/100000,0)*100000,IF(C$48=Параметры!$B$64,ROUNDUP($B$62*(1-Параметры!$B$63)/100000,0)*100000,0)) | D10: =IF(D$48=1,ROUNDUP($B$62*Параметры!$B$63/100000,0)*100000,IF(D$48=Параметры!$B$64,ROUNDUP($B$62*(1-Параметры!$B$63)/100000,0)*100000,0)) | E10: =IF(E$48=1,ROUNDUP($B$62*Параметры!$B$63/100000,0)*100000,IF(E$48=Параметры!$B$64,ROUNDUP($B$62*(1-Параметры!$B$63)/100000,0)*100000,0)) | F10: =IF(F$48=1,ROUNDUP($B$62*Параметры!$B$63/100000,0)*100000,IF(F$48=Параметры!$B$64,ROUNDUP($B$62*(1-Параметры!$B$63)/100000,0)*100000,0)) | G10: =IF(G$48=1,ROUNDUP($B$62*Параметры!$B$63/100000,0)*100000,IF(G$48=Параметры!$B$64,ROUNDUP($B$62*(1-Параметры!$B$63)/100000,0)*100000,0)) | H10: =IF(H$48=1,ROUNDUP($B$62*Параметры!$B$63/100000,0)*100000,IF(H$48=Параметры!$B$64,ROUNDUP($B$62*(1-Параметры!$B$63)/100000,0)*100000,0)) | I10: =IF(I$48=1,ROUNDUP($B$62*Параметры!$B$63/100000,0)*100000,IF(I$48=Параметры!$B$64,ROUNDUP($B$62*(1-Параметры!$B$63)/100000,0)*100000,0)) | ... Y10: =IF(Y$48=1,ROUNDUP($B$62*Параметры!$B$63/100000,0)*100000,IF(Y$48=Параметры!$B$64,ROUNDUP($B$62*(1-Параметры!$B$63)/100000,0)*100000,0)) | Z10: =SUM(B10:Y10)
A11: ПРИХОД ИТОГО | B11: =B10+B9+B6+B3 | C11: =C10+C9+C6+C3 | D11: =D10+D9+D6+D3 | E11: =E10+E9+E6+E3 | F11: =F10+F9+F6+F3 | G11: =G10+G9+G6+G3 | H11: =H10+H9+H6+H3 | I11: =I10+I9+I6+I3 | ... Y11: =Y10+Y9+Y6+Y3 | Z11: =SUM(B11:Y11)
A12: РАСХОД | Z12: =Z17+Z22+Z26+Z34+Z38+Z42+Z43
A13: Разработка сайта и IT (ЗП разработчика, штат) | B13: =ROUND(Параметры!$B$32*IF(B$48<=12,1,1+Параметры!$B$34),0) | C13: =ROUND(Параметры!$B$32*IF(C$48<=12,1,1+Параметры!$B$34),0) | D13: =ROUND(Параметры!$B$32*IF(D$48<=12,1,1+Параметры!$B$34),0) | E13: =ROUND(Параметры!$B$32*IF(E$48<=12,1,1+Параметры!$B$34),0) | F13: =ROUND(Параметры!$B$32*IF(F$48<=12,1,1+Параметры!$B$34),0) | G13: =ROUND(Параметры!$B$32*IF(G$48<=12,1,1+Параметры!$B$34),0) | H13: =ROUND(Параметры!$B$32*IF(H$48<=12,1,1+Параметры!$B$34),0) | I13: =ROUND(Параметры!$B$32*IF(I$48<=12,1,1+Параметры!$B$34),0) | ... Y13: =ROUND(Параметры!$B$32*IF(Y$48<=12,1,1+Параметры!$B$34),0) | Z13: =SUM(B13:Y13)
A14: Техподдержка и дизайн принтов (ЗП дизайнера, штат) | B14: =ROUND(Параметры!$B$33*IF(B$48<=12,1,1+Параметры!$B$34),0) | C14: =ROUND(Параметры!$B$33*IF(C$48<=12,1,1+Параметры!$B$34),0) | D14: =ROUND(Параметры!$B$33*IF(D$48<=12,1,1+Параметры!$B$34),0) | E14: =ROUND(Параметры!$B$33*IF(E$48<=12,1,1+Параметры!$B$34),0) | F14: =ROUND(Параметры!$B$33*IF(F$48<=12,1,1+Параметры!$B$34),0) | G14: =ROUND(Параметры!$B$33*IF(G$48<=12,1,1+Параметры!$B$34),0) | H14: =ROUND(Параметры!$B$33*IF(H$48<=12,1,1+Параметры!$B$34),0) | I14: =ROUND(Параметры!$B$33*IF(I$48<=12,1,1+Параметры!$B$34),0) | ... Y14: =ROUND(Параметры!$B$33*IF(Y$48<=12,1,1+Параметры!$B$34),0) | Z14: =SUM(B14:Y14)
A15: Хостинг | B15: =Параметры!$B$46 | C15: =Параметры!$B$46 | D15: =Параметры!$B$46 | E15: =Параметры!$B$46 | F15: =Параметры!$B$46 | G15: =Параметры!$B$46 | H15: =Параметры!$B$46 | I15: =Параметры!$B$46 | ... Y15: =Параметры!$B$46 | Z15: =SUM(B15:Y15)
A16: Аренда сервера | B16: =Параметры!$B$47 | C16: =Параметры!$B$47 | D16: =Параметры!$B$47 | E16: =Параметры!$B$47 | F16: =Параметры!$B$47 | G16: =Параметры!$B$47 | H16: =Параметры!$B$47 | I16: =Параметры!$B$47 | ... Y16: =Параметры!$B$47 | Z16: =SUM(B16:Y16)
A17: ИТОГО расходы на ИТ | B17: =SUM(B13:B16) | C17: =SUM(C13:C16) | D17: =SUM(D13:D16) | E17: =SUM(E13:E16) | F17: =SUM(F13:F16) | G17: =SUM(G13:G16) | H17: =SUM(H13:H16) | I17: =SUM(I13:I16) | ... Y17: =SUM(Y13:Y16) | Z17: =SUM(B17:Y17)
A18: Бухобслуживание | B18: =Параметры!$B$48 | C18: =Параметры!$B$48 | D18: =Параметры!$B$48 | E18: =Параметры!$B$48 | F18: =Параметры!$B$48 | G18: =Параметры!$B$48 | H18: =Параметры!$B$48 | I18: =Параметры!$B$48 | ... Y18: =Параметры!$B$48 | Z18: =SUM(B18:Y18)
A19: Налоги з/п | B19: =ROUND((B34+B13+B14)*Параметры!$B$35,0) | C19: =ROUND((C34+C13+C14)*Параметры!$B$35,0) | D19: =ROUND((D34+D13+D14)*Параметры!$B$35,0) | E19: =ROUND((E34+E13+E14)*Параметры!$B$35,0) | F19: =ROUND((F34+F13+F14)*Параметры!$B$35,0) | G19: =ROUND((G34+G13+G14)*Параметры!$B$35,0) | H19: =ROUND((H34+H13+H14)*Параметры!$B$35,0) | I19: =ROUND((I34+I13+I14)*Параметры!$B$35,0) | ... Y19: =ROUND((Y34+Y13+Y14)*Параметры!$B$35,0) | Z19: =SUM(B19:Y19)
A20: Налоги прочее | B20: =ROUND(MAX(Параметры!$B$58*((B3+B6+B9)-(B17+B18+B19+B21+B26+B34+B38+B42)),Параметры!$B$59*(B3+B6+B9)),0) | C20: =ROUND(MAX(Параметры!$B$58*((C3+C6+C9)-(C17+C18+C19+C21+C26+C34+C38+C42)),Параметры!$B$59*(C3+C6+C9)),0) | D20: =ROUND(MAX(Параметры!$B$58*((D3+D6+D9)-(D17+D18+D19+D21+D26+D34+D38+D42)),Параметры!$B$59*(D3+D6+D9)),0) | E20: =ROUND(MAX(Параметры!$B$58*((E3+E6+E9)-(E17+E18+E19+E21+E26+E34+E38+E42)),Параметры!$B$59*(E3+E6+E9)),0) | F20: =ROUND(MAX(Параметры!$B$58*((F3+F6+F9)-(F17+F18+F19+F21+F26+F34+F38+F42)),Параметры!$B$59*(F3+F6+F9)),0) | G20: =ROUND(MAX(Параметры!$B$58*((G3+G6+G9)-(G17+G18+G19+G21+G26+G34+G38+G42)),Параметры!$B$59*(G3+G6+G9)),0) | H20: =ROUND(MAX(Параметры!$B$58*((H3+H6+H9)-(H17+H18+H19+H21+H26+H34+H38+H42)),Параметры!$B$59*(H3+H6+H9)),0) | I20: =ROUND(MAX(Параметры!$B$58*((I3+I6+I9)-(I17+I18+I19+I21+I26+I34+I38+I42)),Параметры!$B$59*(I3+I6+I9)),0) | ... Y20: =ROUND(MAX(Параметры!$B$58*((Y3+Y6+Y9)-(Y17+Y18+Y19+Y21+Y26+Y34+Y38+Y42)),Параметры!$B$59*(Y3+Y6+Y9)),0) | Z20: =SUM(B20:Y20)
A21: Эквайринг и комиссии маркетплейсов | B21: =ROUND((B3+B6)*Параметры!$B$49,0) | C21: =ROUND((C3+C6)*Параметры!$B$49,0) | D21: =ROUND((D3+D6)*Параметры!$B$49,0) | E21: =ROUND((E3+E6)*Параметры!$B$49,0) | F21: =ROUND((F3+F6)*Параметры!$B$49,0) | G21: =ROUND((G3+G6)*Параметры!$B$49,0) | H21: =ROUND((H3+H6)*Параметры!$B$49,0) | I21: =ROUND((I3+I6)*Параметры!$B$49,0) | ... Y21: =ROUND((Y3+Y6)*Параметры!$B$49,0) | Z21: =SUM(B21:Y21)
A22: ИТОГО расходы на бухгалтерию | B22: =SUM(B18:B21) | C22: =SUM(C18:C21) | D22: =SUM(D18:D21) | E22: =SUM(E18:E21) | F22: =SUM(F18:F21) | G22: =SUM(G18:G21) | H22: =SUM(H18:H21) | I22: =SUM(I18:I21) | ... Y22: =SUM(Y18:Y21) | Z22: =SUM(B22:Y22)
A23: Реклама интернет (performance, таргет, блогеры) | B23: =ROUND(MAX(Параметры!$B$39,(B3+B6+B9)*Параметры!$B$38),0) | C23: =ROUND(MAX(Параметры!$B$39,(C3+C6+C9)*Параметры!$B$38),0) | D23: =ROUND(MAX(Параметры!$B$39,(D3+D6+D9)*Параметры!$B$38),0) | E23: =ROUND(MAX(Параметры!$B$39,(E3+E6+E9)*Параметры!$B$38),0) | F23: =ROUND(MAX(Параметры!$B$39,(F3+F6+F9)*Параметры!$B$38),0) | G23: =ROUND(MAX(Параметры!$B$39,(G3+G6+G9)*Параметры!$B$38),0) | H23: =ROUND(MAX(Параметры!$B$39,(H3+H6+H9)*Параметры!$B$38),0) | I23: =ROUND(MAX(Параметры!$B$39,(I3+I6+I9)*Параметры!$B$38),0) | ... Y23: =ROUND(MAX(Параметры!$B$39,(Y3+Y6+Y9)*Параметры!$B$38),0) | Z23: =SUM(B23:Y23)
A24: Реклама оффлайн (забеги, спортклубы, амбассадоры) | B24: =IF(B$48<Параметры!$B$41,0,Параметры!$B$40) | C24: =IF(C$48<Параметры!$B$41,0,Параметры!$B$40) | D24: =IF(D$48<Параметры!$B$41,0,Параметры!$B$40) | E24: =IF(E$48<Параметры!$B$41,0,Параметры!$B$40) | F24: =IF(F$48<Параметры!$B$41,0,Параметры!$B$40) | G24: =IF(G$48<Параметры!$B$41,0,Параметры!$B$40) | H24: =IF(H$48<Параметры!$B$41,0,Параметры!$B$40) | I24: =IF(I$48<Параметры!$B$41,0,Параметры!$B$40) | ... Y24: =IF(Y$48<Параметры!$B$41,0,Параметры!$B$40) | Z24: =SUM(B24:Y24)
A25: SЕО Продвижение | B25: =IF(B$48<Параметры!$B$43,0,Параметры!$B$42) | C25: =IF(C$48<Параметры!$B$43,0,Параметры!$B$42) | D25: =IF(D$48<Параметры!$B$43,0,Параметры!$B$42) | E25: =IF(E$48<Параметры!$B$43,0,Параметры!$B$42) | F25: =IF(F$48<Параметры!$B$43,0,Параметры!$B$42) | G25: =IF(G$48<Параметры!$B$43,0,Параметры!$B$42) | H25: =IF(H$48<Параметры!$B$43,0,Параметры!$B$42) | I25: =IF(I$48<Параметры!$B$43,0,Параметры!$B$42) | ... Y25: =IF(Y$48<Параметры!$B$43,0,Параметры!$B$42) | Z25: =SUM(B25:Y25)
A26: ИТОГО расходы на рекламу | B26: =SUM(B23:B25) | C26: =SUM(C23:C25) | D26: =SUM(D23:D25) | E26: =SUM(E23:E25) | F26: =SUM(F23:F25) | G26: =SUM(G23:G25) | H26: =SUM(H23:H25) | I26: =SUM(I23:I25) | ... Y26: =SUM(Y23:Y25) | Z26: =SUM(B26:Y26)
A27: Зп менеджер по продажам 1 (%) | B27: =ROUND((B3+B6+B9)*Параметры!$B$26,0) | C27: =ROUND((C3+C6+C9)*Параметры!$B$26,0) | D27: =ROUND((D3+D6+D9)*Параметры!$B$26,0) | E27: =ROUND((E3+E6+E9)*Параметры!$B$26,0) | F27: =ROUND((F3+F6+F9)*Параметры!$B$26,0) | G27: =ROUND((G3+G6+G9)*Параметры!$B$26,0) | H27: =ROUND((H3+H6+H9)*Параметры!$B$26,0) | I27: =ROUND((I3+I6+I9)*Параметры!$B$26,0) | ... Y27: =ROUND((Y3+Y6+Y9)*Параметры!$B$26,0) | Z27: =SUM(B27:Y27)
A28: Зп менеджер по продажам 2 (%) | B28: =IF(B$48<Параметры!$B$29,0,ROUND((B3+B6+B9)*Параметры!$B$28,0)) | C28: =IF(C$48<Параметры!$B$29,0,ROUND((C3+C6+C9)*Параметры!$B$28,0)) | D28: =IF(D$48<Параметры!$B$29,0,ROUND((D3+D6+D9)*Параметры!$B$28,0)) | E28: =IF(E$48<Параметры!$B$29,0,ROUND((E3+E6+E9)*Параметры!$B$28,0)) | F28: =IF(F$48<Параметры!$B$29,0,ROUND((F3+F6+F9)*Параметры!$B$28,0)) | G28: =IF(G$48<Параметры!$B$29,0,ROUND((G3+G6+G9)*Параметры!$B$28,0)) | H28: =IF(H$48<Параметры!$B$29,0,ROUND((H3+H6+H9)*Параметры!$B$28,0)) | I28: =IF(I$48<Параметры!$B$29,0,ROUND((I3+I6+I9)*Параметры!$B$28,0)) | ... Y28: =IF(Y$48<Параметры!$B$29,0,ROUND((Y3+Y6+Y9)*Параметры!$B$28,0)) | Z28: =SUM(B28:Y28)
A29: Зп маркетолог (%) | B29: =ROUND((B3+B6+B9)*Параметры!$B$31,0) | C29: =ROUND((C3+C6+C9)*Параметры!$B$31,0) | D29: =ROUND((D3+D6+D9)*Параметры!$B$31,0) | E29: =ROUND((E3+E6+E9)*Параметры!$B$31,0) | F29: =ROUND((F3+F6+F9)*Параметры!$B$31,0) | G29: =ROUND((G3+G6+G9)*Параметры!$B$31,0) | H29: =ROUND((H3+H6+H9)*Параметры!$B$31,0) | I29: =ROUND((I3+I6+I9)*Параметры!$B$31,0) | ... Y29: =ROUND((Y3+Y6+Y9)*Параметры!$B$31,0) | Z29: =SUM(B29:Y29)
A30: Зп менеджер по продажам 1 (оклад) | B30: =ROUND(Параметры!$B$25*IF(B$48<=12,1,1+Параметры!$B$34),0) | C30: =ROUND(Параметры!$B$25*IF(C$48<=12,1,1+Параметры!$B$34),0) | D30: =ROUND(Параметры!$B$25*IF(D$48<=12,1,1+Параметры!$B$34),0) | E30: =ROUND(Параметры!$B$25*IF(E$48<=12,1,1+Параметры!$B$34),0) | F30: =ROUND(Параметры!$B$25*IF(F$48<=12,1,1+Параметры!$B$34),0) | G30: =ROUND(Параметры!$B$25*IF(G$48<=12,1,1+Параметры!$B$34),0) | H30: =ROUND(Параметры!$B$25*IF(H$48<=12,1,1+Параметры!$B$34),0) | I30: =ROUND(Параметры!$B$25*IF(I$48<=12,1,1+Параметры!$B$34),0) | ... Y30: =ROUND(Параметры!$B$25*IF(Y$48<=12,1,1+Параметры!$B$34),0) | Z30: =SUM(B30:Y30)
A31: Зп менеджер по продажам 2 (оклад) | B31: =IF(B$48<Параметры!$B$29,0,ROUND(Параметры!$B$27*IF(B$48<=12,1,1+Параметры!$B$34),0)) | C31: =IF(C$48<Параметры!$B$29,0,ROUND(Параметры!$B$27*IF(C$48<=12,1,1+Параметры!$B$34),0)) | D31: =IF(D$48<Параметры!$B$29,0,ROUND(Параметры!$B$27*IF(D$48<=12,1,1+Параметры!$B$34),0)) | E31: =IF(E$48<Параметры!$B$29,0,ROUND(Параметры!$B$27*IF(E$48<=12,1,1+Параметры!$B$34),0)) | F31: =IF(F$48<Параметры!$B$29,0,ROUND(Параметры!$B$27*IF(F$48<=12,1,1+Параметры!$B$34),0)) | G31: =IF(G$48<Параметры!$B$29,0,ROUND(Параметры!$B$27*IF(G$48<=12,1,1+Параметры!$B$34),0)) | H31: =IF(H$48<Параметры!$B$29,0,ROUND(Параметры!$B$27*IF(H$48<=12,1,1+Параметры!$B$34),0)) | I31: =IF(I$48<Параметры!$B$29,0,ROUND(Параметры!$B$27*IF(I$48<=12,1,1+Параметры!$B$34),0)) | ... Y31: =IF(Y$48<Параметры!$B$29,0,ROUND(Параметры!$B$27*IF(Y$48<=12,1,1+Параметры!$B$34),0)) | Z31: =SUM(B31:Y31)
A32: Зп маркетолог (оклад) | B32: =ROUND(Параметры!$B$30*IF(B$48<=12,1,1+Параметры!$B$34),0) | C32: =ROUND(Параметры!$B$30*IF(C$48<=12,1,1+Параметры!$B$34),0) | D32: =ROUND(Параметры!$B$30*IF(D$48<=12,1,1+Параметры!$B$34),0) | E32: =ROUND(Параметры!$B$30*IF(E$48<=12,1,1+Параметры!$B$34),0) | F32: =ROUND(Параметры!$B$30*IF(F$48<=12,1,1+Параметры!$B$34),0) | G32: =ROUND(Параметры!$B$30*IF(G$48<=12,1,1+Параметры!$B$34),0) | H32: =ROUND(Параметры!$B$30*IF(H$48<=12,1,1+Параметры!$B$34),0) | I32: =ROUND(Параметры!$B$30*IF(I$48<=12,1,1+Параметры!$B$34),0) | ... Y32: =ROUND(Параметры!$B$30*IF(Y$48<=12,1,1+Параметры!$B$34),0) | Z32: =SUM(B32:Y32)
A33: ЗП Руководителя | B33: =ROUND(Параметры!$B$24*IF(B$48<=12,1,1+Параметры!$B$34),0) | C33: =ROUND(Параметры!$B$24*IF(C$48<=12,1,1+Параметры!$B$34),0) | D33: =ROUND(Параметры!$B$24*IF(D$48<=12,1,1+Параметры!$B$34),0) | E33: =ROUND(Параметры!$B$24*IF(E$48<=12,1,1+Параметры!$B$34),0) | F33: =ROUND(Параметры!$B$24*IF(F$48<=12,1,1+Параметры!$B$34),0) | G33: =ROUND(Параметры!$B$24*IF(G$48<=12,1,1+Параметры!$B$34),0) | H33: =ROUND(Параметры!$B$24*IF(H$48<=12,1,1+Параметры!$B$34),0) | I33: =ROUND(Параметры!$B$24*IF(I$48<=12,1,1+Параметры!$B$34),0) | ... Y33: =ROUND(Параметры!$B$24*IF(Y$48<=12,1,1+Параметры!$B$34),0) | Z33: =SUM(B33:Y33)
A34: ИТОГО расходы на ФОТ | B34: =SUM(B27:B33) | C34: =SUM(C27:C33) | D34: =SUM(D27:D33) | E34: =SUM(E27:E33) | F34: =SUM(F27:F33) | G34: =SUM(G27:G33) | H34: =SUM(H27:H33) | I34: =SUM(I27:I33) | ... Y34: =SUM(Y27:Y33) | Z34: =SUM(B34:Y34)
A35: Аренда офиса и мини-склада | B35: =Параметры!$B$50 | C35: =Параметры!$B$50 | D35: =Параметры!$B$50 | E35: =Параметры!$B$50 | F35: =Параметры!$B$50 | G35: =Параметры!$B$50 | H35: =Параметры!$B$50 | I35: =Параметры!$B$50 | ... Y35: =Параметры!$B$50 | Z35: =SUM(B35:Y35)
A36: Канцелярия и прочие расходы | B36: =Параметры!$B$51 | C36: =Параметры!$B$51 | D36: =Параметры!$B$51 | E36: =Параметры!$B$51 | F36: =Параметры!$B$51 | G36: =Параметры!$B$51 | H36: =Параметры!$B$51 | I36: =Параметры!$B$51 | ... Y36: =Параметры!$B$51 | Z36: =SUM(B36:Y36)
A37: Связь и интернет | B37: =Параметры!$B$52 | C37: =Параметры!$B$52 | D37: =Параметры!$B$52 | E37: =Параметры!$B$52 | F37: =Параметры!$B$52 | G37: =Параметры!$B$52 | H37: =Параметры!$B$52 | I37: =Параметры!$B$52 | ... Y37: =Параметры!$B$52 | Z37: =SUM(B37:Y37)
A38: ИТОГО админастративные расходы | B38: =SUM(B35:B37) | C38: =SUM(C35:C37) | D38: =SUM(D35:D37) | E38: =SUM(E35:E37) | F38: =SUM(F35:F37) | G38: =SUM(G35:G37) | H38: =SUM(H35:H37) | I38: =SUM(I35:I37) | ... Y38: =SUM(Y35:Y37) | Z38: =SUM(B38:Y38)
A39: Себестоимость товара (пошив, печать, закупка) | B39: =B50+IF(Параметры!$B$55=1,C50,0) | C39: =C50 | D39: =D50 | E39: =E50 | F39: =F50 | G39: =G50 | H39: =H50 | I39: =I50 | J39: =J50 | ... Y39: =Y50 | Z39: =SUM(B39:Y39)
A40: Логистика и фулфилмент | B40: =ROUND((B3+B6+B9)*Параметры!$B$53,0) | C40: =ROUND((C3+C6+C9)*Параметры!$B$53,0) | D40: =ROUND((D3+D6+D9)*Параметры!$B$53,0) | E40: =ROUND((E3+E6+E9)*Параметры!$B$53,0) | F40: =ROUND((F3+F6+F9)*Параметры!$B$53,0) | G40: =ROUND((G3+G6+G9)*Параметры!$B$53,0) | H40: =ROUND((H3+H6+H9)*Параметры!$B$53,0) | I40: =ROUND((I3+I6+I9)*Параметры!$B$53,0) | ... Y40: =ROUND((Y3+Y6+Y9)*Параметры!$B$53,0) | Z40: =SUM(B40:Y40)
A41: Упаковка, брак и возвраты | B41: =ROUND((B3+B6)*Параметры!$B$54,0) | C41: =ROUND((C3+C6)*Параметры!$B$54,0) | D41: =ROUND((D3+D6)*Параметры!$B$54,0) | E41: =ROUND((E3+E6)*Параметры!$B$54,0) | F41: =ROUND((F3+F6)*Параметры!$B$54,0) | G41: =ROUND((G3+G6)*Параметры!$B$54,0) | H41: =ROUND((H3+H6)*Параметры!$B$54,0) | I41: =ROUND((I3+I6)*Параметры!$B$54,0) | ... Y41: =ROUND((Y3+Y6)*Параметры!$B$54,0) | Z41: =SUM(B41:Y41)
A42: ИТОГО прочие расходы | B42: =SUM(B39:B41) | C42: =SUM(C39:C41) | D42: =SUM(D39:D41) | E42: =SUM(E39:E41) | F42: =SUM(F39:F41) | G42: =SUM(G39:G41) | H42: =SUM(H39:H41) | I42: =SUM(I39:I41) | ... Y42: =SUM(Y39:Y41) | Z42: =SUM(B42:Y42)
A43: ВОЗВРАТ ИНВЕСТИЦИЙ | B43: =MIN(B49,ROUND(MAX(0,B53)*Параметры!$B$66,0),MAX(0,Параметры!$B$70+B11-(B17+B22+B26+B34+B38+B42)-Параметры!$B$67)) | C43: =MIN(C49,ROUND(MAX(0,C53)*Параметры!$B$66,0),MAX(0,B46+C11-(C17+C22+C26+C34+C38+C42)-Параметры!$B$67)) | D43: =MIN(D49,ROUND(MAX(0,D53)*Параметры!$B$66,0),MAX(0,C46+D11-(D17+D22+D26+D34+D38+D42)-Параметры!$B$67)) | E43: =MIN(E49,ROUND(MAX(0,E53)*Параметры!$B$66,0),MAX(0,D46+E11-(E17+E22+E26+E34+E38+E42)-Параметры!$B$67)) | F43: =MIN(F49,ROUND(MAX(0,F53)*Параметры!$B$66,0),MAX(0,E46+F11-(F17+F22+F26+F34+F38+F42)-Параметры!$B$67)) | G43: =MIN(G49,ROUND(MAX(0,G53)*Параметры!$B$66,0),MAX(0,F46+G11-(G17+G22+G26+G34+G38+G42)-Параметры!$B$67)) | H43: =MIN(H49,ROUND(MAX(0,H53)*Параметры!$B$66,0),MAX(0,G46+H11-(H17+H22+H26+H34+H38+H42)-Параметры!$B$67)) | I43: =MIN(I49,ROUND(MAX(0,I53)*Параметры!$B$66,0),MAX(0,H46+I11-(I17+I22+I26+I34+I38+I42)-Параметры!$B$67)) | J43: =MIN(J49,ROUND(MAX(0,J53)*Параметры!$B$66,0),MAX(0,I46+J11-(J17+J22+J26+J34+J38+J42)-Параметры!$B$67)) | ... Y43: =MIN(Y49,ROUND(MAX(0,Y53)*Параметры!$B$66,0),MAX(0,X46+Y11-(Y17+Y22+Y26+Y34+Y38+Y42)-Параметры!$B$67)) | Z43: =SUM(B43:Y43) | AA43: =ROUND($Z$10*Параметры!$B$65,0)-$Z$43 | AB43: осталось вернуть инвестиций
A44: РАСХОД ИТОГО | B44: =SUM(B43,B42,B38,B34,B26,B22,B17) | C44: =SUM(C43,C42,C38,C34,C26,C22,C17) | D44: =SUM(D43,D42,D38,D34,D26,D22,D17) | E44: =SUM(E43,E42,E38,E34,E26,E22,E17) | F44: =SUM(F43,F42,F38,F34,F26,F22,F17) | G44: =SUM(G43,G42,G38,G34,G26,G22,G17) | H44: =SUM(H43,H42,H38,H34,H26,H22,H17) | I44: =SUM(I43,I42,I38,I34,I26,I22,I17) | ... Y44: =SUM(Y43,Y42,Y38,Y34,Y26,Y22,Y17) | Z44: =SUM(B44:Y44)
A45: Сальдо | B45: =B11-B44 | C45: =C11-C44 | D45: =D11-D44 | E45: =E11-E44 | F45: =F11-F44 | G45: =G11-G44 | H45: =H11-H44 | I45: =I11-I44 | ... Y45: =Y11-Y44 | Z45: =SUM(B45:Y45)
A46: Ден. Поток | B46: =B47+B45 | C46: =B46+C45 | D46: =C46+D45 | E46: =D46+E45 | F46: =E46+F45 | G46: =F46+G45 | H46: =G46+H45 | I46: =H46+I45 | J46: =I46+J45 | ... Y46: =X46+Y45
A47: Сальдо на начало периода | B47: =Параметры!$B$70
A48: № месяца | B48: =1 | C48: =B48+1 | D48: =C48+1 | E48: =D48+1 | F48: =E48+1 | G48: =F48+1 | H48: =G48+1 | I48: =H48+1 | J48: =I48+1 | ... Y48: =X48+1
A49: Остаток обязательства перед инвестором (на начало мес.) | B49: =ROUND(B10*Параметры!$B$65,0) | C49: =B49-B43+ROUND(C10*Параметры!$B$65,0) | D49: =C49-C43+ROUND(D10*Параметры!$B$65,0) | E49: =D49-D43+ROUND(E10*Параметры!$B$65,0) | F49: =E49-E43+ROUND(F10*Параметры!$B$65,0) | G49: =F49-F43+ROUND(G10*Параметры!$B$65,0) | H49: =G49-G43+ROUND(H10*Параметры!$B$65,0) | I49: =H49-H43+ROUND(I10*Параметры!$B$65,0) | J49: =I49-I43+ROUND(J10*Параметры!$B$65,0) | ... Y49: =X49-X43+ROUND(Y10*Параметры!$B$65,0)
A50: Себестоимость проданного товара (справочно) | B50: =ROUND(B4*Параметры!$B$5+B7*Параметры!$B$7+B9*Параметры!$B$9,0) | C50: =ROUND(C4*Параметры!$B$5+C7*Параметры!$B$7+C9*Параметры!$B$9,0) | D50: =ROUND(D4*Параметры!$B$5+D7*Параметры!$B$7+D9*Параметры!$B$9,0) | E50: =ROUND(E4*Параметры!$B$5+E7*Параметры!$B$7+E9*Параметры!$B$9,0) | F50: =ROUND(F4*Параметры!$B$5+F7*Параметры!$B$7+F9*Параметры!$B$9,0) | G50: =ROUND(G4*Параметры!$B$5+G7*Параметры!$B$7+G9*Параметры!$B$9,0) | H50: =ROUND(H4*Параметры!$B$5+H7*Параметры!$B$7+H9*Параметры!$B$9,0) | I50: =ROUND(I4*Параметры!$B$5+I7*Параметры!$B$7+I9*Параметры!$B$9,0) | ... Y50: =ROUND(Y4*Параметры!$B$5+Y7*Параметры!$B$7+Y9*Параметры!$B$9,0) | Z50: =SUM(B50:Y50)
A51: Валовая прибыль | B51: =(B3+B6+B9)-B50 | C51: =(C3+C6+C9)-C50 | D51: =(D3+D6+D9)-D50 | E51: =(E3+E6+E9)-E50 | F51: =(F3+F6+F9)-F50 | G51: =(G3+G6+G9)-G50 | H51: =(H3+H6+H9)-H50 | I51: =(I3+I6+I9)-I50 | ... Y51: =(Y3+Y6+Y9)-Y50 | Z51: =SUM(B51:Y51)
A52: Валовая маржа, % | B52: =IF((B3+B6+B9)=0,0,B51/(B3+B6+B9)) | C52: =IF((C3+C6+C9)=0,0,C51/(C3+C6+C9)) | D52: =IF((D3+D6+D9)=0,0,D51/(D3+D6+D9)) | E52: =IF((E3+E6+E9)=0,0,E51/(E3+E6+E9)) | F52: =IF((F3+F6+F9)=0,0,F51/(F3+F6+F9)) | G52: =IF((G3+G6+G9)=0,0,G51/(G3+G6+G9)) | H52: =IF((H3+H6+H9)=0,0,H51/(H3+H6+H9)) | I52: =IF((I3+I6+I9)=0,0,I51/(I3+I6+I9)) | ... Z52: =IF((Z3+Z6+Z9)=0,0,Z51/(Z3+Z6+Z9))
A53: Операционный ден. поток (без инвестиций и возврата) | B53: =(B3+B6+B9)-(B17+B22+B26+B34+B38+B42) | C53: =(C3+C6+C9)-(C17+C22+C26+C34+C38+C42) | D53: =(D3+D6+D9)-(D17+D22+D26+D34+D38+D42) | E53: =(E3+E6+E9)-(E17+E22+E26+E34+E38+E42) | F53: =(F3+F6+F9)-(F17+F22+F26+F34+F38+F42) | G53: =(G3+G6+G9)-(G17+G22+G26+G34+G38+G42) | H53: =(H3+H6+H9)-(H17+H22+H26+H34+H38+H42) | I53: =(I3+I6+I9)-(I17+I22+I26+I34+I38+I42) | ... Y53: =(Y3+Y6+Y9)-(Y17+Y22+Y26+Y34+Y38+Y42) | Z53: =SUM(B53:Y53)
A54: Накопленный операционный ден. поток | B54: =B53 | C54: =B54+C53 | D54: =C54+D53 | E54: =D54+E53 | F54: =E54+F53 | G54: =F54+G53 | H54: =G54+H53 | I54: =H54+I53 | J54: =I54+J53 | ... Y54: =X54+Y53
A55: Денежный поток инвестора (−транш / +возврат) | B55: =B43-B10 | C55: =C43-C10 | D55: =D43-D10 | E55: =E43-E10 | F55: =F43-F10 | G55: =G43-G10 | H55: =H43-H10 | I55: =I43-I10 | ... Y55: =Y43-Y10 | Z55: =SUM(B55:Y55)
A56: флаг: месяц выхода в операционный плюс | B56: =IF(B53>0,B$48,9999) | C56: =IF(C53>0,C$48,9999) | D56: =IF(D53>0,D$48,9999) | E56: =IF(E53>0,E$48,9999) | F56: =IF(F53>0,F$48,9999) | G56: =IF(G53>0,G$48,9999) | H56: =IF(H53>0,H$48,9999) | I56: =IF(I53>0,I$48,9999) | ... Y56: =IF(Y53>0,Y$48,9999)
A57: флаг: месяц окупаемости проекта | B57: =IF(B54>0,B$48,9999) | C57: =IF(C54>0,C$48,9999) | D57: =IF(D54>0,D$48,9999) | E57: =IF(E54>0,E$48,9999) | F57: =IF(F54>0,F$48,9999) | G57: =IF(G54>0,G$48,9999) | H57: =IF(H54>0,H$48,9999) | I57: =IF(I54>0,I$48,9999) | ... Y57: =IF(Y54>0,Y$48,9999)
A58: флаг: месяц полного возврата инвестору | B58: =IF(AND(B49>0,B49-B43<=0.5),B$48,9999) | C58: =IF(AND(C49>0,C49-C43<=0.5),C$48,9999) | D58: =IF(AND(D49>0,D49-D43<=0.5),D$48,9999) | E58: =IF(AND(E49>0,E49-E43<=0.5),E$48,9999) | F58: =IF(AND(F49>0,F49-F43<=0.5),F$48,9999) | G58: =IF(AND(G49>0,G49-G43<=0.5),G$48,9999) | H58: =IF(AND(H49>0,H49-H43<=0.5),H$48,9999) | I58: =IF(AND(I49>0,I49-I43<=0.5),I$48,9999) | ... Y58: =IF(AND(Y49>0,Y49-Y43<=0.5),Y$48,9999)
A60: КЛЮЧЕВЫЕ ПОКАЗАТЕЛИ ДЛЯ ИНВЕСТОРА
A61: Пиковая потребность в деньгах (макс. кассовый разрыв) | B61: =MAX(0,-MIN(B54:Y54)) | C61: считается моделью автоматически
A62: Требуемые инвестиции (с запасом прочности) | B62: =ROUNDUP(B61*(1+Параметры!$B$62)/100000,0)*100000 | C62: именно эту сумму просим у инвестора
A63: Транш 1 (месяц 1) | B63: =B10
A64: Транш 2 | B64: =$Z$10-B10 | C64: по достижении KPI
A65: Привлечено инвестиций всего | B65: =$Z$10
A66: Обязательство перед инвестором (тело × коэффициент) | B66: =ROUND($Z$10*Параметры!$B$65,0)
A67: Возвращено инвестору за 24 месяца | B67: =$Z$43
A68: Остаток обязательства на конец горизонта | B68: =$AA$43
A69: Доход инвестора за 24 месяца | B69: =$Z$43-$Z$10
A70: ROI инвестора за 24 месяца | B70: =IF($Z$10=0,0,($Z$43-$Z$10)/$Z$10)
A71: IRR инвестора, % годовых | B71: =IFERROR((1+IRR(B55:Y55))^12-1,"н/д") | C71: по потоку «транш → возвраты»
A72: IRR проекта, % годовых | B72: =IFERROR((1+IRR(B53:Y53))^12-1,"н/д") | C72: по операционному потоку
A73: NPV проекта | B73: =ROUND(NPV(Параметры!$B$68/12,B53:Y53),0) | C73: ставка дисконтирования — на листе Параметры
A74: Месяц выхода в операционный плюс | B74: =IF(MIN(B56:Y56)=9999,"за горизонтом",MIN(B56:Y56))
A75: Месяц окупаемости проекта (накопленный поток > 0) | B75: =IF(MIN(B57:Y57)=9999,"за горизонтом",MIN(B57:Y57))
A76: Месяц полного возврата инвестору | B76: =IF(MIN(B58:Y58)=9999,"за горизонтом",MIN(B58:Y58))
A77: Выручка за 24 месяца | B77: =$Z$3+$Z$6+$Z$9
A78: Выручка в 24-м месяце (run-rate) | B78: =$Y$3+$Y$6+$Y$9
A79: Средняя валовая маржа | B79: =IF(B77=0,0,($Z$51)/B77)
A80: Операционная прибыль за 24 месяца | B80: =$Z$53
A81: Рентабельность по операционному потоку | B81: =IF(B77=0,0,B80/B77)
A82: Минимальный остаток на счёте за горизонт | B82: =MIN(B46:Y46)
A83: Проверка достаточности денег | B83: =IF(B82>=0,"ОК: кассовых разрывов нет","ДЕФИЦИТ: поднимите запас прочности")
A84: Оценка компании post-money (по доле инвестора) | B84: =IF(Параметры!$B$69=0,0,ROUND($Z$10/Параметры!$B$69,0)) | C84: альтернатива долговому возврату

Sheet Параметры
A1: ПАРАМЕТРЫ ФИНМОДЕЛИ — кейс «Спортивные футболки» | C1: D2C-бренд + маркетплейсы + B2B-экипировка. Горизонт 24 месяца, ₽
A2: Меняйте ТОЛЬКО жёлтые ячейки этого листа — весь ДДС пересчитается сам
A3: 1. ПРОДУКТ И ЮНИТ-ЭКОНОМИКА
A4: Товар 1 «Базовая» — средний чек | B4: 1890 | C4: розница: сайт + маркетплейсы
A5: Товар 1 «Базовая» — себестоимость | B5: 680 | C5: полотно, пошив, печать, бирка, брак
A6: Товар 2 «Pro / кастом-принт» — средний чек | B6: 3200 | C6: влагоотводящая ткань, кастом
A7: Товар 2 «Pro / кастом-принт» — себестоимость | B7: 1200
A8: Товар 3 «B2B командная экипировка» — средний чек заказа | B8: 42000 | C8: партия от 20 шт
A9: Товар 3 — себестоимость, % от чека | B9: 0.55 | C9: опт: маржа ниже, объём выше
A11: 2. ОБЪЁМЫ ПРОДАЖ И РОСТ | B11: 2 | C11: СЦЕНАРИЙ: 1 — пессимистичный, 2 — базовый, 3 — оптимистичный → | D11: 1 — пессимистичный | E11: 2 — базовый | F11: 3 — оптимистичный
A12: Товар 1 — продажи в 1-й месяц, шт | B12: =CHOOSE($B$11,D12,E12,F12) | C12: ≈ 20 шт/день на старте | D12: 520 | E12: 600 | F12: 700
A13: Товар 1 — рост продаж в месяц, 1-й год | B13: =CHOOSE($B$11,D13,E13,F13) | D13: 0.11 | E13: 0.12 | F13: 0.14
A14: Товар 1 — рост продаж в месяц, 2-й год | B14: =CHOOSE($B$11,D14,E14,F14) | C14: замедление на масштабе | D14: 0.04 | E14: 0.05 | F14: 0.06
A15: Товар 2 — старт продаж, № месяца | B15: 3
A16: Товар 2 — продажи в 1-й месяц запуска, шт | B16: =CHOOSE($B$11,D16,E16,F16) | D16: 100 | E16: 120 | F16: 150
A17: Товар 2 — рост продаж в месяц, 1-й год | B17: =CHOOSE($B$11,D17,E17,F17) | D17: 0.13 | E17: 0.15 | F17: 0.17
A18: Товар 2 — рост продаж в месяц, 2-й год | B18: 0.07
A19: Товар 3 (B2B) — старт продаж, № месяца | B19: 5 | C19: после первых отзывов и портфолио
A20: Товар 3 (B2B) — заказов в 1-й месяц запуска, шт | B20: =CHOOSE($B$11,D20,E20,F20) | D20: 4 | E20: 5 | F20: 7
A21: Товар 3 (B2B) — рост выручки в месяц | B21: 0.1
A23: 3. КОМАНДА — 6 ЧЕЛОВЕК (оклады gross, ₽/мес)
A24: 1. Руководитель проекта (CEO) — оклад | B24: 120000 | C24: строка ДДС «ЗП Руководителя»
A25: 2. Менеджер по продажам 1 — оклад | B25: 45000 | C25: с 1-го месяца
A26: 2. Менеджер по продажам 1 — % от выручки | B26: 0.02
A27: 3. Менеджер по продажам 2 — оклад | B27: 45000
A28: 3. Менеджер по продажам 2 — % от выручки | B28: 0.02
A29: 3. Менеджер по продажам 2 — выход, № месяца | B29: 3 | C29: нанимаем под запуск товара 2
A30: 4. Маркетолог — оклад | B30: 70000
A31: 4. Маркетолог — % от выручки | B31: 0.01
A32: 5. Разработчик / поддержка сайта — оклад | B32: 90000 | C32: строка ДДС «Разработка»
A33: 6. Дизайнер принтов и контента — оклад | B33: 65000 | C33: строка ДДС «Техническая поддержка»
A34: Индексация окладов со 2-го года | B34: 0.1
A35: Страховые взносы, % от ФОТ | B35: 0.2 | C35: льготный тариф МСП (среднее)
A37: 4. МАРКЕТИНГ
A38: Реклама интернет, % от выручки | B38: 0.14 | C38: performance, таргет, блогеры
A39: Реклама интернет — минимальный бюджет, ₽/мес | B39: 350000 | C39: разгон трафика на старте
A40: Реклама оффлайн, ₽/мес | B40: 80000 | C40: забеги, спортклубы, амбассадоры
A41: Реклама оффлайн — старт, № месяца | B41: 5
A42: SEO-продвижение, ₽/мес | B42: 60000
A43: SEO — старт, № месяца | B43: 2
A45: 5. IT, АДМИНИСТРАТИВНЫЕ И ОПЕРАЦИОННЫЕ РАСХОДЫ
A46: Хостинг и домен, ₽/мес | B46: 8000
A47: Аренда сервера, CRM и сервисы, ₽/мес | B47: 12000
A48: Бухобслуживание (аутсорс), ₽/мес | B48: 25000
A49: Эквайринг и комиссии маркетплейсов, % от B2C-выручки | B49: 0.09 | C49: ≈ половина продаж через маркетплейсы
A50: Аренда офиса и мини-склада, ₽/мес | B50: 90000
A51: Канцелярия, ПО и прочее, ₽/мес | B51: 15000
A52: Связь и интернет, ₽/мес | B52: 12000
A53: Логистика и фулфилмент, % от выручки | B53: 0.06 | C53: часть доставки платит покупатель
A54: Упаковка, брак и возвраты, % от B2C-выручки | B54: 0.05
A55: Первоначальный товарный запас (1 = формируем, 0 = нет) | B55: 1 | C55: в мес. 1 закупаем товар ещё и под продажи мес. 2
A57: 6. НАЛОГИ
A58: УСН «Доходы минус расходы», ставка | B58: 0.15
A59: Минимальный налог, % от доходов | B59: 0.01 | C59: платим, если он больше расчётного
A61: 7. УСЛОВИЯ СДЕЛКИ С ИНВЕСТОРОМ
A62: Запас прочности к пиковой потребности | B62: 0.25 | C62: буфер на отклонение от плана
A63: Доля 1-го транша (месяц 1) | B63: 0.8
A64: 2-й транш — № месяца | B64: 6 | C64: по достижении KPI по выручке
A65: Коэффициент возврата инвестору, × | B65: 1.8 | C65: возвращаем тело + доход: 1,8× вложенного
A66: Доля операционного потока на возврат инвестору | B66: 0.75
A67: Неснижаемый остаток на счёте (подушка), ₽ | B67: 300000
A68: Ставка дисконтирования, % годовых | B68: 0.25 | C68: для NPV
A69: Доля инвестора в капитале | B69: 0.2 | C69: для оценки post-money
A70: Сальдо на начало проекта, ₽ | B70: 0 | C70: собственных средств нет
A72: 8. ЮНИТ-ЭКОНОМИКА (расчёт)
A73: Маржа с товара 1, ₽ | B73: =B4-B5
A74: Маржа с товара 1, % | B74: =IF(B4=0,0,(B4-B5)/B4)
A75: Маржа с товара 2, ₽ | B75: =B6-B7
A76: Маржа с товара 2, % | B76: =IF(B6=0,0,(B6-B7)/B6)
A77: Маржа с B2B-заказа, ₽ | B77: =B8*(1-B9)
A78: Маржа с B2B-заказа, % | B78: =1-B9

Sheet Питч
A1: ПИТЧ ИНВЕСТОРУ — «СПОРТИВНЫЕ ФУТБОЛКИ»
A3: Проблема | C3: Спортивная одежда в РФ после ухода мировых брендов: покупатель хочет качество и быструю кастомизацию, а получает либо дорогой импорт, либо безликий ноунейм.
A4: Решение | C4: D2C-бренд спортивных футболок: собственный сайт + маркетплейсы + печать под заказ. Срок от заказа до отгрузки — 3 дня, кастом-принт от 1 шт.
A5: Продукт | C5: 1) «Базовая» — массовый спрос; 2) «Pro / кастом-принт» — высокая маржа; 3) B2B — экипировка для команд, клубов и корпоративных забегов.
A6: Бизнес-модель | C6: Контрактное производство (без CAPEX на оборудование) + собственный трафик. Деньги инвестора идут в товарный запас и маркетинг, а не в железо.
A8: ЮНИТ-ЭКОНОМИКА
A9: Средний чек «Базовая» | B9: =Параметры!B4 | C9: розница, сайт и маркетплейсы
A10: Маржа «Базовая» | B10: =Параметры!B74
A11: Маржа «Pro / кастом» | B11: =Параметры!B76
A12: Маржа B2B-заказа | B12: =Параметры!B78
A13: Средняя валовая маржа проекта | B13: =ДДС!B79
A15: КОМАНДА — 6 ЧЕЛОВЕК
A16: 1. Руководитель проекта (CEO) | B16: =Параметры!B24 | C16: стратегия, продукт, инвестор
A17: 2. Менеджер по продажам 1 | B17: =Параметры!B25 | C17: розница и маркетплейсы, + % от выручки
A18: 3. Менеджер по продажам 2 | B18: =Параметры!B27 | C18: B2B-направление, выходит с 4-го месяца
A19: 4. Маркетолог | B19: =Параметры!B30 | C19: трафик, бренд, амбассадоры, + % от выручки
A20: 5. Разработчик / поддержка сайта | B20: =Параметры!B32 | C20: сайт, интеграции с маркетплейсами
A21: 6. Дизайнер принтов и контента | B21: =Параметры!B33 | C21: коллекции, визуал, кастом-макеты
A22: Итого ФОТ первого месяца (с взносами) | B22: =ДДС!B34+ДДС!B13+ДДС!B14+ДДС!B19
A24: ЗАПРОС И УСЛОВИЯ СДЕЛКИ
A25: Требуемые инвестиции | B25: =ДДС!B62 | C25: двумя траншами, под KPI по выручке
A26: Транш 1 (месяц 1) | B26: =ДДС!B63 | C26: товарный запас + разгон трафика
A27: Транш 2 | B27: =ДДС!B64 | C27: масштабирование после подтверждения спроса
A28: Возврат инвестору за 24 мес. | B28: =ДДС!B67 | C28: из операционного потока
A29: Доход инвестора | B29: =ДДС!B69
A30: ROI инвестора за 24 мес. | B30: =ДДС!B70
A31: IRR инвестора, % годовых | B31: =ДДС!B71
A32: Альтернатива: оценка post-money | B32: =ДДС!B84 | C32: при доле инвестора на листе Параметры
A34: ЭКОНОМИКА ПРОЕКТА ЗА 24 МЕСЯЦА
A35: Сценарий модели (1 песс. / 2 базовый / 3 опт.) | B35: =Параметры!B11 | C35: переключается одной ячейкой на листе «Параметры»
A36: Выручка за 24 месяца | B36: =ДДС!B77
A37: Выручка в 24-м месяце (run-rate) | B37: =ДДС!B78
A38: Операционная прибыль за 24 месяца | B38: =ДДС!B80
A39: Рентабельность по операционному потоку | B39: =ДДС!B81
A40: NPV проекта (ставка 25% годовых) | B40: =ДДС!B73
A41: Месяц выхода в операционный плюс | B41: =ДДС!B74
A42: Месяц окупаемости проекта | B42: =ДДС!B75
A43: Месяц полного возврата инвестору | B43: =ДДС!B76
A44: Минимальный остаток на счёте | B44: =ДДС!B82
A45: Проверка достаточности денег | B45: =ДДС!B83
A47: РИСКИ И ОТВЕТ НА НИХ
A48: Спрос ниже плана | C48: Модель на формулах: снижаем рост продаж на листе «Параметры» и сразу видим новую потребность в деньгах. Реклама привязана к % от выручки — бюджет не «горит».
A49: Рост себестоимости / курс | C49: Контрактное производство в РФ, два поставщика, себестоимость — параметр модели.
A50: Кассовый разрыв | C50: Неснижаемый остаток на счёте и возврат инвестору только из операционного потока.
A51: Уход ключевого человека | C51: Команда 6 человек, у продавцов и маркетолога % от выручки — доход привязан к результату.
